my_quiz_plugin/__init__.py
my_quiz_plugin/plugin.py
tests/__init__.py
tests/base_test_case.py
tests/mock_quiz_data.py
tests/test_html_generation.py
tests/test_logic.py
tests/test_mock.py
tests/test_ui_components.py
my_quiz_plugin-2.0.1.dist-info/LICENSE
my_quiz_plugin-2.0.1.dist-info/METADATA
my_quiz_plugin-2.0.1.dist-info/WHEEL
my_quiz_plugin-2.0.1.dist-info/entry_points.txt
my_quiz_plugin-2.0.1.dist-info/top_level.txt
my_quiz_plugin-2.0.1.dist-info/RECORD
